fixdates/__init__.py
fixdates/main.py
fixdates-0.0.11.dist-info/LICENSE
fixdates-0.0.11.dist-info/METADATA
fixdates-0.0.11.dist-info/WHEEL
fixdates-0.0.11.dist-info/entry_points.txt
fixdates-0.0.11.dist-info/top_level.txt
fixdates-0.0.11.dist-info/RECORD
