Metadata-Version: 2.1
Name: fixdates
Version: 0.0.11
Summary: A simple program to parse and clean date string to standardized date string dd-mmm-yyyy. Useful in pre-processing prior to conversion to proper date data type.
Author-email: Zaid Waqi <zaidwaqi@gmail.com>
License: GPLv3
Project-URL: Homepage, https://github.com/zaidwaqi/fixdates
Project-URL: Issues, https://github.com/pypa/zaidwaqi/fixdates/issues
Classifier: Programming Language :: Python :: 3
Classifier: License :: OSI Approved :: GNU General Public License v3 (GPLv3)
Classifier: Operating System :: OS Independent
Requires-Python: >=3.9
License-File: LICENSE
